{
  "listedItems": [
    {
      "sellerName": "aubreigh",
      "saleItem": {
        "id": 13199,
        "amount": 1
      },
      "price": 117000,
      "timeListed": 1635277026904,
      "amountSold": 0,
      "profit": 0,
      "transactionTime": 0,
      "buyersInfo": []
    },
    {
      "sellerName": "aubreigh",
      "lastBuyerName": "Mangomen",
      "saleItem": {
        "id": 22002,
        "amount": 1
      },
      "price": 175000,
      "timeListed": 1635277066500,
      "amountSold": 1,
      "profit": 175000,
      "transactionTime": 1635363698122,
      "buyersInfo": [
        "Mangomen"
      ]
    }
  ]
}