{
  "listedItems": [
    {
      "sellerName": "care plane",
      "saleItem": {
        "id": 30228,
        "amount": 2
      },
      "price": 1950000,
      "timeListed": 1634809455877,
      "amountSold": 0,
      "profit": 0,
      "transactionTime": 0,
      "buyersInfo": []
    },
    {
      "sellerName": "care plane",
      "lastBuyerName": "K O O P A",
      "saleItem": {
        "id": 12081,
        "amount": 2
      },
      "price": 5000000,
      "timeListed": 1634809438480,
      "amountSold": 2,
      "profit": 10000000,
      "transactionTime": 1635084434249,
      "buyersInfo": [
        "Free Da Guys",
        "K O O P A"
      ]
    },
    {
      "sellerName": "care plane",
      "saleItem": {
        "id": 26502,
        "amount": 1
      },
      "price": 6500000,
      "timeListed": 1634809464284,
      "amountSold": 0,
      "profit": 0,
      "transactionTime": 0,
      "buyersInfo": []
    }
  ]
}