{
  "listedItems": [
    {
      "sellerName": "lyria",
      "saleItem": {
        "id": 13197,
        "amount": 1
      },
      "price": 199000,
      "timeListed": 1635163628898,
      "amountSold": 0,
      "profit": 0,
      "transactionTime": 0,
      "buyersInfo": []
    },
    {
      "sellerName": "lyria",
      "saleItem": {
        "id": 12821,
        "amount": 1
      },
      "price": 149000,
      "timeListed": 1635163657089,
      "amountSold": 0,
      "profit": 0,
      "transactionTime": 0,
      "buyersInfo": []
    },
    {
      "sellerName": "lyria",
      "lastBuyerName": "Crackrock",
      "saleItem": {
        "id": 11785,
        "amount": 1
      },
      "price": 89000,
      "timeListed": 1635163984697,
      "amountSold": 1,
      "profit": 89000,
      "transactionTime": 1635187021889,
      "buyersInfo": [
        "Crackrock"
      ]
    }
  ]
}